[{"id":"ton_EQCVflRjTn91FKGZzy2UTHgLn3hG3TsOlQIsAOPcB57K5gT5","paircoin":{"name":"FISH / TON","baseImg":"https://assets.coingecko.com/coins/images/34651/small/FISH_LOGO.png?1705597359","quoteImg":"https://assets.coingecko.com/coins/images/17980/small/ton_symbol.png?1696517498","pooladdress":"EQCVflRjTn91FKGZzy2UTHgLn3hG3TsOlQIsAOPcB57K5gT5","dexname":"stonfi","basename":"TON FISH MEMECOIN","quotename":"Toncoin","baseSymbol":"FISH","quoteSymbol":"TON","baseaddress":"EQATcUc69sGSCCMSadsVUKdGwM1BMKS-HKCWGPk60xZGgwsK","quoteaddress":"EQAAAAAAAAAAAAAAAAAAAAAAAAAAAAAAAAAAAAAAAAAAAM9c","basecoinId":"ton-fish-memecoin","quotecoinId":null},"name":"FISH / TON","basename":"TON FISH MEMECOIN","quotename":"Toncoin","baseSymbol":"FISH","quoteSymbol":"TON","baseImg":"https://assets.coingecko.com/coins/images/34651/small/FISH_LOGO.png?1705597359","quoteImg":"https://assets.coingecko.com/coins/images/17980/small/ton_symbol.png?1696517498","baseaddress":"EQATcUc69sGSCCMSadsVUKdGwM1BMKS-HKCWGPk60xZGgwsK","quoteaddress":"EQAAAAAAAAAAAAAAAAAAAAAAAAAAAAAAAAAAAAAAAAAAAM9c","basecoinId":"ton-fish-memecoin","quotecoinId":null,"created":"2024-01-02T10:53:01Z","pooladdress":"EQCVflRjTn91FKGZzy2UTHgLn3hG3TsOlQIsAOPcB57K5gT5","baseprice":"0.000000126874774261685","quoteprice":"4.07","fdv":"53374949","cap":null,"price_change_percentage":{"m5":"-0.68","h1":"0.26","h6":"-7.39","h24":"-7.63"},"transactions":{"m5":{"buys":4,"sells":4,"buyers":4,"sellers":4},"m15":{"buys":11,"sells":4,"buyers":10,"sellers":4},"m30":{"buys":18,"sells":13,"buyers":17,"sellers":12},"h1":{"buys":36,"sells":25,"buyers":34,"sellers":21},"h24":{"buys":1683,"sells":1080,"buyers":1240,"sellers":830}},"volume_usd":{"m5":"3890.45811095843","h1":"29544.3341924773","h6":"237098.595867769","h24":"1246740.393186"},"reserve":"1641484.9316","dex":"stonfi"},{"id":"ton_EQCqFPpSLtcstURtrXLRCv9wyjfrw7_44_nwvD8JiSmSjbUI","paircoin":{"name":"RAFF / TON","baseImg":"missing.png","quoteImg":"https://assets.coingecko.com/coins/images/17980/small/ton_symbol.png?1696517498","pooladdress":"EQCqFPpSLtcstURtrXLRCv9wyjfrw7_44_nwvD8JiSmSjbUI","dexname":"stonfi","basename":"Ton Raffles Token","quotename":"Toncoin","baseSymbol":"RAFF","quoteSymbol":"TON","baseaddress":"EQCJbp0kBpPwPoBG-U5C-cWfP_jnksvotGfArPF50Q9Qiv9h","quoteaddress":"EQAAAAAAAAAAAAAAAAAAAAAAAAAAAAAAAAAAAAAAAAAAAM9c","basecoinId":null,"quotecoinId":null},"name":"RAFF / TON","basename":"Ton Raffles Token","quotename":"Toncoin","baseSymbol":"RAFF","quoteSymbol":"TON","baseImg":"missing.png","quoteImg":"https://assets.coingecko.com/coins/images/17980/small/ton_symbol.png?1696517498","baseaddress":"EQCJbp0kBpPwPoBG-U5C-cWfP_jnksvotGfArPF50Q9Qiv9h","quoteaddress":"EQAAAAAAAAAAAAAAAAAAAAAAAAAAAAAAAAAAAAAAAAAAAM9c","basecoinId":null,"quotecoinId":null,"created":"2023-12-13T00:13:01Z","pooladdress":"EQCqFPpSLtcstURtrXLRCv9wyjfrw7_44_nwvD8JiSmSjbUI","baseprice":"0.849834995483944","quoteprice":"4.07","fdv":"16996700","cap":null,"price_change_percentage":{"m5":"0.07","h1":"0.08","h6":"-0.66","h24":"9.92"},"transactions":{"m5":{"buys":3,"sells":0,"buyers":3,"sellers":0},"m15":{"buys":17,"sells":1,"buyers":17,"sellers":1},"m30":{"buys":28,"sells":6,"buyers":27,"sellers":6},"h1":{"buys":48,"sells":13,"buyers":45,"sellers":13},"h24":{"buys":2160,"sells":475,"buyers":1840,"sellers":411}},"volume_usd":{"m5":"726.87011507055","h1":"11427.2176407804","h6":"72739.503895822","h24":"359003.177271318"},"reserve":"2153780.1252","dex":"stonfi"},{"id":"ton_EQASBZLwa2vfdsgoDF2w96pdccBJJRxDNXXPUL7NMm0WdnMx","paircoin":{"name":"GRAM / TON","baseImg":"https://assets.geckoterminal.com/gtoy7uhj5plief7jhn37tygqspq8","quoteImg":"https://assets.coingecko.com/coins/images/17980/small/ton_symbol.png?1696517498","pooladdress":"EQASBZLwa2vfdsgoDF2w96pdccBJJRxDNXXPUL7NMm0WdnMx","dexname":"stonfi","basename":"Gram","quotename":"Toncoin","baseSymbol":"GRAM","quoteSymbol":"TON","baseaddress":"EQC47093oX5Xhb0xuk2lCr2RhS8rj-vul61u4W2UH5ORmG_O","quoteaddress":"EQAAAAAAAAAAAAAAAAAAAAAAAAAAAAAAAAAAAAAAAAAAAM9c","basecoinId":null,"quotecoinId":null},"name":"GRAM / TON","basename":"Gram","quotename":"Toncoin","baseSymbol":"GRAM","quoteSymbol":"TON","baseImg":"https://assets.geckoterminal.com/gtoy7uhj5plief7jhn37tygqspq8","quoteImg":"https://assets.coingecko.com/coins/images/17980/small/ton_symbol.png?1696517498","baseaddress":"EQC47093oX5Xhb0xuk2lCr2RhS8rj-vul61u4W2UH5ORmG_O","quoteaddress":"EQAAAAAAAAAAAAAAAAAAAAAAAAAAAAAAAAAAAAAAAAAAAM9c","basecoinId":null,"quotecoinId":null,"created":"2024-01-31T14:43:03Z","pooladdress":"EQASBZLwa2vfdsgoDF2w96pdccBJJRxDNXXPUL7NMm0WdnMx","baseprice":"0.02739395758191","quoteprice":"4.07","fdv":"136969788","cap":null,"price_change_percentage":{"m5":"-0.6","h1":"0.67","h6":"7.69","h24":"-13.05"},"transactions":{"m5":{"buys":1,"sells":1,"buyers":1,"sellers":1},"m15":{"buys":6,"sells":2,"buyers":6,"sellers":2},"m30":{"buys":18,"sells":5,"buyers":16,"sellers":5},"h1":{"buys":31,"sells":14,"buyers":29,"sellers":12},"h24":{"buys":1576,"sells":1053,"buyers":1129,"sellers":775}},"volume_usd":{"m5":"150.14431483722","h1":"6700.95668206217","h6":"408010.953880594","h24":"1680353.9240388"},"reserve":"3899458.8883","dex":"stonfi"},{"id":"ton_EQDtZHOtVWaf9UIU6rmjLPNLTGxNLNogvK5xUZlMRgZwQ4Gt","paircoin":{"name":"STON / TON","baseImg":"https://assets.coingecko.com/coins/images/31233/small/STON.jpg?1696530059","quoteImg":"https://assets.coingecko.com/coins/images/17980/small/ton_symbol.png?1696517498","pooladdress":"EQDtZHOtVWaf9UIU6rmjLPNLTGxNLNogvK5xUZlMRgZwQ4Gt","dexname":"stonfi","basename":"STON","quotename":"Toncoin","baseSymbol":"STON","quoteSymbol":"TON","baseaddress":"EQA2kCVNwVsil2EM2mB0SkXytxCqQjS4mttjDpnXmwG9T6bO","quoteaddress":"EQAAAAAAAAAAAAAAAAAAAAAAAAAAAAAAAAAAAAAAAAAAAM9c","basecoinId":"ston-2","quotecoinId":null},"name":"STON / TON","basename":"STON","quotename":"Toncoin","baseSymbol":"STON","quoteSymbol":"TON","baseImg":"https://assets.coingecko.com/coins/images/31233/small/STON.jpg?1696530059","quoteImg":"https://assets.coingecko.com/coins/images/17980/small/ton_symbol.png?1696517498","baseaddress":"EQA2kCVNwVsil2EM2mB0SkXytxCqQjS4mttjDpnXmwG9T6bO","quoteaddress":"EQAAAAAAAAAAAAAAAAAAAAAAAAAAAAAAAAAAAAAAAAAAAM9c","basecoinId":"ston-2","quotecoinId":null,"created":"2023-11-20T03:07:17Z","pooladdress":"EQDtZHOtVWaf9UIU6rmjLPNLTGxNLNogvK5xUZlMRgZwQ4Gt","baseprice":"11.9919968418443","quoteprice":"4.07","fdv":"1199199683","cap":null,"price_change_percentage":{"m5":"0.45","h1":"1.35","h6":"0.34","h24":"2.32"},"transactions":{"m5":{"buys":4,"sells":2,"buyers":4,"sellers":2},"m15":{"buys":8,"sells":2,"buyers":8,"sellers":2},"m30":{"buys":19,"sells":6,"buyers":12,"sellers":5},"h1":{"buys":32,"sells":11,"buyers":22,"sellers":9},"h24":{"buys":954,"sells":489,"buyers":650,"sellers":314}},"volume_usd":{"m5":"1592.84985294831","h1":"11749.0737092129","h6":"118140.799578267","h24":"504487.731966283"},"reserve":"3826823.7942","dex":"stonfi"},{"id":"ton_EQCZBr4PnOkRCZLa-PKo0o9zTGRjp10_YhWCV2syVB3VHU04","paircoin":{"name":"MRDN / TON","baseImg":"missing.png","quoteImg":"https://assets.coingecko.com/coins/images/17980/small/ton_symbol.png?1696517498","pooladdress":"EQCZBr4PnOkRCZLa-PKo0o9zTGRjp10_YhWCV2syVB3VHU04","dexname":"stonfi","basename":"Meridian","quotename":"Toncoin","baseSymbol":"MRDN","quoteSymbol":"TON","baseaddress":"EQCymLRXp1QYxZKek4CTInckB1ey5TkyAJQpPAlNetiO54Vt","quoteaddress":"EQAAAAAAAAAAAAAAAAAAAAAAAAAAAAAAAAAAAAAAAAAAAM9c","basecoinId":null,"quotecoinId":null},"name":"MRDN / TON","basename":"Meridian","quotename":"Toncoin","baseSymbol":"MRDN","quoteSymbol":"TON","baseImg":"missing.png","quoteImg":"https://assets.coingecko.com/coins/images/17980/small/ton_symbol.png?1696517498","baseaddress":"EQCymLRXp1QYxZKek4CTInckB1ey5TkyAJQpPAlNetiO54Vt","quoteaddress":"EQAAAAAAAAAAAAAAAAAAAAAAAAAAAAAAAAAAAAAAAAAAAM9c","basecoinId":null,"quotecoinId":null,"created":"2024-02-07T12:53:03Z","pooladdress":"EQCZBr4PnOkRCZLa-PKo0o9zTGRjp10_YhWCV2syVB3VHU04","baseprice":"0.00367277254845453","quoteprice":"4.07","fdv":"181064","cap":null,"price_change_percentage":{"m5":"0","h1":"-17.51","h6":"-2.86","h24":"-10.46"},"transactions":{"m5":{"buys":0,"sells":1,"buyers":0,"sellers":1},"m15":{"buys":5,"sells":2,"buyers":5,"sellers":2},"m30":{"buys":10,"sells":8,"buyers":7,"sellers":8},"h1":{"buys":19,"sells":17,"buyers":13,"sellers":14},"h24":{"buys":616,"sells":649,"buyers":259,"sellers":170}},"volume_usd":{"m5":"29.48914988811","h1":"3583.97438809114","h6":"23047.0679305658","h24":"126442.036819712"},"reserve":"14491.4466","dex":"stonfi"},{"id":"ton_EQAda1uHzS5iWf9fT6IyrNgtvRzMECOFGhlNvNFT3FQF3HqW","paircoin":{"name":"CAT / TON","baseImg":"https://assets.geckoterminal.com/htur0vwlb2dvr42nm3vy7922gzcd","quoteImg":"https://assets.coingecko.com/coins/images/17980/small/ton_symbol.png?1696517498","pooladdress":"EQAda1uHzS5iWf9fT6IyrNgtvRzMECOFGhlNvNFT3FQF3HqW","dexname":"stonfi","basename":"CatTonEmojis","quotename":"Toncoin","baseSymbol":"CAT","quoteSymbol":"TON","baseaddress":"EQAApzIfA-vfYmqpyzmYCKR15CLlcz33tEJPfvgH68heBITn","quoteaddress":"EQAAAAAAAAAAAAAAAAAAAAAAAAAAAAAAAAAAAAAAAAAAAM9c","basecoinId":null,"quotecoinId":null},"name":"CAT / TON","basename":"CatTonEmojis","quotename":"Toncoin","baseSymbol":"CAT","quoteSymbol":"TON","baseImg":"https://assets.geckoterminal.com/htur0vwlb2dvr42nm3vy7922gzcd","quoteImg":"https://assets.coingecko.com/coins/images/17980/small/ton_symbol.png?1696517498","baseaddress":"EQAApzIfA-vfYmqpyzmYCKR15CLlcz33tEJPfvgH68heBITn","quoteaddress":"EQAAAAAAAAAAAAAAAAAAAAAAAAAAAAAAAAAAAAAAAAAAAM9c","basecoinId":null,"quotecoinId":null,"created":"2024-03-21T02:33:06Z","pooladdress":"EQAda1uHzS5iWf9fT6IyrNgtvRzMECOFGhlNvNFT3FQF3HqW","baseprice":"0.000117759363273032","quoteprice":"4.07","fdv":"117759","cap":null,"price_change_percentage":{"m5":"0.05","h1":"19.19","h6":"-12.23","h24":"5882.66"},"transactions":{"m5":{"buys":2,"sells":0,"buyers":2,"sellers":0},"m15":{"buys":9,"sells":0,"buyers":9,"sellers":0},"m30":{"buys":11,"sells":1,"buyers":11,"sellers":1},"h1":{"buys":18,"sells":6,"buyers":16,"sellers":5},"h24":{"buys":675,"sells":380,"buyers":388,"sellers":175}},"volume_usd":{"m5":"3.21191198141","h1":"1270.27193880797","h6":"8324.48464773967","h24":"69287.4607591227"},"reserve":"14047.3658","dex":"stonfi"},{"id":"ton_EQCKRr2ry9l3RUh6i19h93ueygoWTayadsd9DQv8vgEYvhYc","paircoin":{"name":"TONY / TON","baseImg":"https://assets.geckoterminal.com/lkgnkmijp5spzgicqdu8ojgxgvtt","quoteImg":"https://assets.coingecko.com/coins/images/17980/small/ton_symbol.png?1696517498","pooladdress":"EQCKRr2ry9l3RUh6i19h93ueygoWTayadsd9DQv8vgEYvhYc","dexname":"stonfi","basename":"TONY THE DUCK","quotename":"Toncoin","baseSymbol":"TONY","quoteSymbol":"TON","baseaddress":"EQBiJd6z0WiuiCQdywPOqaLyT2TbTfV79Pzu9K1R3l_qlUZ5","quoteaddress":"EQAAAAAAAAAAAAAAAAAAAAAAAAAAAAAAAAAAAAAAAAAAAM9c","basecoinId":null,"quotecoinId":null},"name":"TONY / TON","basename":"TONY THE DUCK","quotename":"Toncoin","baseSymbol":"TONY","quoteSymbol":"TON","baseImg":"https://assets.geckoterminal.com/lkgnkmijp5spzgicqdu8ojgxgvtt","quoteImg":"https://assets.coingecko.com/coins/images/17980/small/ton_symbol.png?1696517498","baseaddress":"EQBiJd6z0WiuiCQdywPOqaLyT2TbTfV79Pzu9K1R3l_qlUZ5","quoteaddress":"EQAAAAAAAAAAAAAAAAAAAAAAAAAAAAAAAAAAAAAAAAAAAM9c","basecoinId":null,"quotecoinId":null,"created":"2024-03-13T19:33:04Z","pooladdress":"EQCKRr2ry9l3RUh6i19h93ueygoWTayadsd9DQv8vgEYvhYc","baseprice":"0.00281526651517953","quoteprice":"4.07","fdv":"2815267","cap":null,"price_change_percentage":{"m5":"0.07","h1":"16.65","h6":"31.21","h24":"100.27"},"transactions":{"m5":{"buys":2,"sells":0,"buyers":2,"sellers":0},"m15":{"buys":8,"sells":3,"buyers":8,"sellers":3},"m30":{"buys":11,"sells":5,"buyers":11,"sellers":5},"h1":{"buys":16,"sells":8,"buyers":16,"sellers":8},"h24":{"buys":649,"sells":406,"buyers":462,"sellers":309}},"volume_usd":{"m5":"105.82","h1":"14235.3743555125","h6":"43110.6514074001","h24":"316261.276603264"},"reserve":"282038.4207","dex":"stonfi"},{"id":"ton_EQAX8VVdiemDa-Y0ew2fWebXW-gUA9QzjM4IkEnZ7WbEF8yR","paircoin":{"name":"@BTC25 / TON","baseImg":"https://assets.geckoterminal.com/z292oay47m9yz7ripmatuj4ibrcw","quoteImg":"https://assets.coingecko.com/coins/images/17980/small/ton_symbol.png?1696517498","pooladdress":"EQAX8VVdiemDa-Y0ew2fWebXW-gUA9QzjM4IkEnZ7WbEF8yR","dexname":"stonfi","basename":"@BTC25 MEMECOIN TonMiner","quotename":"Toncoin","baseSymbol":"@BTC25","quoteSymbol":"TON","baseaddress":"EQC7rnHHtMVBKyhiGnAbtYIlzGxS0dfi3ZbHExFX0LYi9cAH","quoteaddress":"EQAAAAAAAAAAAAAAAAAAAAAAAAAAAAAAAAAAAAAAAAAAAM9c","basecoinId":null,"quotecoinId":null},"name":"@BTC25 / TON","basename":"@BTC25 MEMECOIN TonMiner","quotename":"Toncoin","baseSymbol":"@BTC25","quoteSymbol":"TON","baseImg":"https://assets.geckoterminal.com/z292oay47m9yz7ripmatuj4ibrcw","quoteImg":"https://assets.coingecko.com/coins/images/17980/small/ton_symbol.png?1696517498","baseaddress":"EQC7rnHHtMVBKyhiGnAbtYIlzGxS0dfi3ZbHExFX0LYi9cAH","quoteaddress":"EQAAAAAAAAAAAAAAAAAAAAAAAAAAAAAAAAAAAAAAAAAAAM9c","basecoinId":null,"quotecoinId":null,"created":"2024-03-06T04:33:03Z","pooladdress":"EQAX8VVdiemDa-Y0ew2fWebXW-gUA9QzjM4IkEnZ7WbEF8yR","baseprice":"0.00000000608478382433788","quoteprice":"4.07","fdv":"2559808","cap":null,"price_change_percentage":{"m5":"0","h1":"-7.92","h6":"-12.08","h24":"-19.08"},"transactions":{"m5":{"buys":1,"sells":0,"buyers":1,"sellers":0},"m15":{"buys":3,"sells":3,"buyers":3,"sellers":3},"m30":{"buys":7,"sells":7,"buyers":7,"sellers":6},"h1":{"buys":16,"sells":19,"buyers":14,"sellers":18},"h24":{"buys":581,"sells":427,"buyers":373,"sellers":329}},"volume_usd":{"m5":"182.54351473347","h1":"9646.0184013939","h6":"35321.3266407527","h24":"207423.849934201"},"reserve":"202697.3554","dex":"stonfi"},{"id":"ton_EQDFrJJjzBIHDSZ94wb-MtsIkbolBz4Zs2SLOhYDOCHFXPk2","paircoin":{"name":"TFLOKI / TON","baseImg":"https://assets.geckoterminal.com/k2m3yp2k7u9upgjg1qzohc8yu5gv","quoteImg":"https://assets.coingecko.com/coins/images/17980/small/ton_symbol.png?1696517498","pooladdress":"EQDFrJJjzBIHDSZ94wb-MtsIkbolBz4Zs2SLOhYDOCHFXPk2","dexname":"stonfi","basename":"Ton Floki","quotename":"Toncoin","baseSymbol":"TFLOKI","quoteSymbol":"TON","baseaddress":"EQBoIKGcbR9Qdbz8B4k-r8SIt5YpSRmRN3Rrb2ssVTEsiWAd","quoteaddress":"EQAAAAAAAAAAAAAAAAAAAAAAAAAAAAAAAAAAAAAAAAAAAM9c","basecoinId":null,"quotecoinId":null},"name":"TFLOKI / TON","basename":"Ton Floki","quotename":"Toncoin","baseSymbol":"TFLOKI","quoteSymbol":"TON","baseImg":"https://assets.geckoterminal.com/k2m3yp2k7u9upgjg1qzohc8yu5gv","quoteImg":"https://assets.coingecko.com/coins/images/17980/small/ton_symbol.png?1696517498","baseaddress":"EQBoIKGcbR9Qdbz8B4k-r8SIt5YpSRmRN3Rrb2ssVTEsiWAd","quoteaddress":"EQAAAAAAAAAAAAAAAAAAAAAAAAAAAAAAAAAAAAAAAAAAAM9c","basecoinId":null,"quotecoinId":null,"created":"2024-03-16T17:43:08Z","pooladdress":"EQDFrJJjzBIHDSZ94wb-MtsIkbolBz4Zs2SLOhYDOCHFXPk2","baseprice":"0.00359514090505196","quoteprice":"4.07","fdv":"35951.41","cap":null,"price_change_percentage":{"m5":"0","h1":"5.68","h6":"46.28","h24":"158.11"},"transactions":{"m5":{"buys":1,"sells":0,"buyers":1,"sellers":0},"m15":{"buys":4,"sells":4,"buyers":4,"sellers":4},"m30":{"buys":10,"sells":9,"buyers":10,"sellers":8},"h1":{"buys":19,"sells":21,"buyers":18,"sellers":16},"h24":{"buys":491,"sells":467,"buyers":272,"sellers":265}},"volume_usd":{"m5":"36.23173206697","h1":"1837.87140968597","h6":"10311.287995152","h24":"40232.5785501875"},"reserve":"7561.047","dex":"stonfi"},{"id":"ton_EQAKleHU6-eGDQUfi4YXMNve4UQP0RGAIRkU4AiRRlgDUbaM","paircoin":{"name":"jUSDT / TON","baseImg":"https://assets.geckoterminal.com/xhsnpizl70mvyuijshdm9kei6ztq","quoteImg":"https://assets.coingecko.com/coins/images/17980/small/ton_symbol.png?1696517498","pooladdress":"EQAKleHU6-eGDQUfi4YXMNve4UQP0RGAIRkU4AiRRlgDUbaM","dexname":"stonfi","basename":"jUSDT","quotename":"Toncoin","baseSymbol":"jUSDT","quoteSymbol":"TON","baseaddress":"EQBynBO23ywHy_CgarY9NK9FTz0yDsG82PtcbSTQgGoXwiuA","quoteaddress":"EQAAAAAAAAAAAAAAAAAAAAAAAAAAAAAAAAAAAAAAAAAAAM9c","basecoinId":null,"quotecoinId":null},"name":"jUSDT / TON","basename":"jUSDT","quotename":"Toncoin","baseSymbol":"jUSDT","quoteSymbol":"TON","baseImg":"https://assets.geckoterminal.com/xhsnpizl70mvyuijshdm9kei6ztq","quoteImg":"https://assets.coingecko.com/coins/images/17980/small/ton_symbol.png?1696517498","baseaddress":"EQBynBO23ywHy_CgarY9NK9FTz0yDsG82PtcbSTQgGoXwiuA","quoteaddress":"EQAAAAAAAAAAAAAAAAAAAAAAAAAAAAAAAAAAAAAAAAAAAM9c","basecoinId":null,"quotecoinId":null,"created":"2023-11-20T03:07:14Z","pooladdress":"EQAKleHU6-eGDQUfi4YXMNve4UQP0RGAIRkU4AiRRlgDUbaM","baseprice":"1.00197077252684","quoteprice":"4.07","fdv":"1715769","cap":null,"price_change_percentage":{"m5":"0","h1":"-0.68","h6":"0.24","h24":"0.51"},"transactions":{"m5":{"buys":0,"sells":1,"buyers":0,"sellers":1},"m15":{"buys":1,"sells":3,"buyers":1,"sellers":3},"m30":{"buys":3,"sells":3,"buyers":3,"sellers":3},"h1":{"buys":14,"sells":10,"buyers":11,"sellers":10},"h24":{"buys":523,"sells":433,"buyers":298,"sellers":271}},"volume_usd":{"m5":"240.24812312567","h1":"6127.8120885019","h6":"75562.9704297985","h24":"387955.424960323"},"reserve":"1400883.5739","dex":"stonfi"},{"id":"ton_EQAZFS5dJ8STrKcn5VnptYsoKILXbAYaDhdJJjbzUrNkDdH_","paircoin":{"name":"FNZ / TON","baseImg":"https://assets.geckoterminal.com/07256tb687ckqxcfevlae244x2m2","quoteImg":"https://assets.coingecko.com/coins/images/17980/small/ton_symbol.png?1696517498","pooladdress":"EQAZFS5dJ8STrKcn5VnptYsoKILXbAYaDhdJJjbzUrNkDdH_","dexname":"stonfi","basename":"Fanzee Token","quotename":"Toncoin","baseSymbol":"FNZ","quoteSymbol":"TON","baseaddress":"EQDCJL0iQHofcBBvFBHdVG233Ri2V4kCNFgfRT-gqAd3Oc86","quoteaddress":"EQAAAAAAAAAAAAAAAAAAAAAAAAAAAAAAAAAAAAAAAAAAAM9c","basecoinId":null,"quotecoinId":null},"name":"FNZ / TON","basename":"Fanzee Token","quotename":"Toncoin","baseSymbol":"FNZ","quoteSymbol":"TON","baseImg":"https://assets.geckoterminal.com/07256tb687ckqxcfevlae244x2m2","quoteImg":"https://assets.coingecko.com/coins/images/17980/small/ton_symbol.png?1696517498","baseaddress":"EQDCJL0iQHofcBBvFBHdVG233Ri2V4kCNFgfRT-gqAd3Oc86","quoteaddress":"EQAAAAAAAAAAAAAAAAAAAAAAAAAAAAAAAAAAAAAAAAAAAM9c","basecoinId":null,"quotecoinId":null,"created":"2023-11-20T03:07:17Z","pooladdress":"EQAZFS5dJ8STrKcn5VnptYsoKILXbAYaDhdJJjbzUrNkDdH_","baseprice":"0.0175297222092509","quoteprice":"4.07","fdv":"36812416","cap":null,"price_change_percentage":{"m5":"0","h1":"-1.98","h6":"2.08","h24":"20.37"},"transactions":{"m5":{"buys":0,"sells":1,"buyers":0,"sellers":1},"m15":{"buys":4,"sells":2,"buyers":4,"sellers":1},"m30":{"buys":16,"sells":2,"buyers":15,"sellers":1},"h1":{"buys":36,"sells":12,"buyers":33,"sellers":11},"h24":{"buys":738,"sells":191,"buyers":613,"sellers":161}},"volume_usd":{"m5":"1752.97222092509","h1":"5588.70539566799","h6":"52974.2007324668","h24":"130381.946051617"},"reserve":"873029.2701","dex":"stonfi"},{"id":"ton_EQATnq6W2xv10C19LNlC26xFtTV1fbzMkXmXQCWHqtv6Okf7","paircoin":{"name":"JETTON / TON","baseImg":"https://assets.coingecko.com/coins/images/31360/small/jetton.jpeg?1696530177","quoteImg":"https://assets.coingecko.com/coins/images/17980/small/ton_symbol.png?1696517498","pooladdress":"EQATnq6W2xv10C19LNlC26xFtTV1fbzMkXmXQCWHqtv6Okf7","dexname":"stonfi","basename":"JetTon","quotename":"Toncoin","baseSymbol":"JETTON","quoteSymbol":"TON","baseaddress":"EQAQXlWJvGbbFfE8F3oS8s87lIgdovS455IsWFaRdmJetTon","quoteaddress":"EQAAAAAAAAAAAAAAAAAAAAAAAAAAAAAAAAAAAAAAAAAAAM9c","basecoinId":"jetton","quotecoinId":null},"name":"JETTON / TON","basename":"JetTon","quotename":"Toncoin","baseSymbol":"JETTON","quoteSymbol":"TON","baseImg":"https://assets.coingecko.com/coins/images/31360/small/jetton.jpeg?1696530177","quoteImg":"https://assets.coingecko.com/coins/images/17980/small/ton_symbol.png?1696517498","baseaddress":"EQAQXlWJvGbbFfE8F3oS8s87lIgdovS455IsWFaRdmJetTon","quoteaddress":"EQAAAAAAAAAAAAAAAAAAAAAAAAAAAAAAAAAAAAAAAAAAAM9c","basecoinId":"jetton","quotecoinId":null,"created":"2023-11-20T03:07:15Z","pooladdress":"EQATnq6W2xv10C19LNlC26xFtTV1fbzMkXmXQCWHqtv6Okf7","baseprice":"1.88790390144247","quoteprice":"4.07","fdv":"188790390","cap":null,"price_change_percentage":{"m5":"0","h1":"0.18","h6":"0.9","h24":"-8.06"},"transactions":{"m5":{"buys":1,"sells":0,"buyers":1,"sellers":0},"m15":{"buys":2,"sells":1,"buyers":2,"sellers":1},"m30":{"buys":4,"sells":3,"buyers":4,"sellers":3},"h1":{"buys":8,"sells":5,"buyers":7,"sellers":4},"h24":{"buys":343,"sells":354,"buyers":198,"sellers":158}},"volume_usd":{"m5":"2.035","h1":"369.18049026926","h6":"14621.7771961043","h24":"97754.3211674152"},"reserve":"1587190.5425","dex":"stonfi"},{"id":"ton_EQCMKZxZPQ-WQ9AdkQG1Hbg8JE37lBP5pEbTCoRxgdmN63jW","paircoin":{"name":"TONK / TON","baseImg":"https://assets.geckoterminal.com/r5ikj66n55f9oy8orrxnmr1gxrnr","quoteImg":"https://assets.coingecko.com/coins/images/17980/small/ton_symbol.png?1696517498","pooladdress":"EQCMKZxZPQ-WQ9AdkQG1Hbg8JE37lBP5pEbTCoRxgdmN63jW","dexname":"stonfi","basename":"Tonk Inu","quotename":"Toncoin","baseSymbol":"TONK","quoteSymbol":"TON","baseaddress":"EQDv68b3JaWBO_DrP6u13Oq7KsnKhR926kMxcOJwACDY_uQC","quoteaddress":"EQAAAAAAAAAAAAAAAAAAAAAAAAAAAAAAAAAAAAAAAAAAAM9c","basecoinId":null,"quotecoinId":null},"name":"TONK / TON","basename":"Tonk Inu","quotename":"Toncoin","baseSymbol":"TONK","quoteSymbol":"TON","baseImg":"https://assets.geckoterminal.com/r5ikj66n55f9oy8orrxnmr1gxrnr","quoteImg":"https://assets.coingecko.com/coins/images/17980/small/ton_symbol.png?1696517498","baseaddress":"EQDv68b3JaWBO_DrP6u13Oq7KsnKhR926kMxcOJwACDY_uQC","quoteaddress":"EQAAAAAAAAAAAAAAAAAAAAAAAAAAAAAAAAAAAAAAAAAAAM9c","basecoinId":null,"quotecoinId":null,"created":"2024-01-20T16:13:01Z","pooladdress":"EQCMKZxZPQ-WQ9AdkQG1Hbg8JE37lBP5pEbTCoRxgdmN63jW","baseprice":"0.0379676040924076","quoteprice":"4.07","fdv":"3796760","cap":null,"price_change_percentage":{"m5":"0","h1":"-2.7","h6":"2.26","h24":"-10.19"},"transactions":{"m5":{"buys":0,"sells":1,"buyers":0,"sellers":1},"m15":{"buys":0,"sells":2,"buyers":0,"sellers":2},"m30":{"buys":0,"sells":5,"buyers":0,"sellers":5},"h1":{"buys":1,"sells":7,"buyers":1,"sellers":7},"h24":{"buys":566,"sells":124,"buyers":129,"sellers":97}},"volume_usd":{"m5":"241.93313052084","h1":"2181.63340929071","h6":"24621.1418055722","h24":"133773.757861277"},"reserve":"315307.783","dex":"stonfi"},{"id":"ton_EQBCwe_IObXA4Mt3RbcHil2s4-v4YQS3wUDt1-DvZOceeMGO","paircoin":{"name":"REDO / TON","baseImg":"https://assets.geckoterminal.com/iclheb98qneohaoskm1439wnv8oh","quoteImg":"https://assets.coingecko.com/coins/images/17980/small/ton_symbol.png?1696517498","pooladdress":"EQBCwe_IObXA4Mt3RbcHil2s4-v4YQS3wUDt1-DvZOceeMGO","dexname":"stonfi","basename":"Resistance Dog","quotename":"Toncoin","baseSymbol":"REDO","quoteSymbol":"TON","baseaddress":"EQBZ_cafPyDr5KUTs0aNxh0ZTDhkpEZONmLJA2SNGlLm4Cko","quoteaddress":"EQAAAAAAAAAAAAAAAAAAAAAAAAAAAAAAAAAAAAAAAAAAAM9c","basecoinId":null,"quotecoinId":null},"name":"REDO / TON","basename":"Resistance Dog","quotename":"Toncoin","baseSymbol":"REDO","quoteSymbol":"TON","baseImg":"https://assets.geckoterminal.com/iclheb98qneohaoskm1439wnv8oh","quoteImg":"https://assets.coingecko.com/coins/images/17980/small/ton_symbol.png?1696517498","baseaddress":"EQBZ_cafPyDr5KUTs0aNxh0ZTDhkpEZONmLJA2SNGlLm4Cko","quoteaddress":"EQAAAAAAAAAAAAAAAAAAAAAAAAAAAAAAAAAAAAAAAAAAAM9c","basecoinId":null,"quotecoinId":null,"created":"2024-01-09T13:13:01Z","pooladdress":"EQBCwe_IObXA4Mt3RbcHil2s4-v4YQS3wUDt1-DvZOceeMGO","baseprice":"0.166135183826632","quoteprice":"4.07","fdv":"16613518","cap":null,"price_change_percentage":{"m5":"-0.72","h1":"2.9","h6":"2","h24":"-17.57"},"transactions":{"m5":{"buys":1,"sells":2,"buyers":1,"sellers":2},"m15":{"buys":3,"sells":4,"buyers":3,"sellers":4},"m30":{"buys":5,"sells":5,"buyers":5,"sellers":5},"h1":{"buys":9,"sells":6,"buyers":9,"sellers":6},"h24":{"buys":338,"sells":305,"buyers":217,"sellers":208}},"volume_usd":{"m5":"1067.51178898287","h1":"9643.32294407927","h6":"108126.910267155","h24":"341280.760903606"},"reserve":"330738.0601","dex":"stonfi"},{"id":"ton_EQAt0NZhl-vKWcK1CpzJDdYKRkYR6GKKUN4dbAeFw2BeOe8o","paircoin":{"name":"Reshib / TON","baseImg":"missing.png","quoteImg":"https://assets.coingecko.com/coins/images/17980/small/ton_symbol.png?1696517498","pooladdress":"EQAt0NZhl-vKWcK1CpzJDdYKRkYR6GKKUN4dbAeFw2BeOe8o","dexname":"stonfi","basename":"ResistanceShiba","quotename":"Toncoin","baseSymbol":"Reshib","quoteSymbol":"TON","baseaddress":"EQAG3p6kmQtvV71FBOh_xFoH-AmJJXGGI0LjmD24MEXhpSbs","quoteaddress":"EQAAAAAAAAAAAAAAAAAAAAAAAAAAAAAAAAAAAAAAAAAAAM9c","basecoinId":null,"quotecoinId":null},"name":"Reshib / TON","basename":"ResistanceShiba","quotename":"Toncoin","baseSymbol":"Reshib","quoteSymbol":"TON","baseImg":"missing.png","quoteImg":"https://assets.coingecko.com/coins/images/17980/small/ton_symbol.png?1696517498","baseaddress":"EQAG3p6kmQtvV71FBOh_xFoH-AmJJXGGI0LjmD24MEXhpSbs","quoteaddress":"EQAAAAAAAAAAAAAAAAAAAAAAAAAAAAAAAAAAAAAAAAAAAM9c","basecoinId":null,"quotecoinId":null,"created":"2024-03-21T20:03:05Z","pooladdress":"EQAt0NZhl-vKWcK1CpzJDdYKRkYR6GKKUN4dbAeFw2BeOe8o","baseprice":"0.00143274951164676","quoteprice":"4.07","fdv":"14327.50","cap":null,"price_change_percentage":{"m5":"-0.66","h1":"85.1","h6":"2733.69","h24":"2733.69"},"transactions":{"m5":{"buys":1,"sells":1,"buyers":1,"sellers":1},"m15":{"buys":9,"sells":2,"buyers":8,"sellers":2},"m30":{"buys":12,"sells":3,"buyers":10,"sellers":3},"h1":{"buys":14,"sells":3,"buyers":11,"sellers":3},"h24":{"buys":390,"sells":188,"buyers":214,"sellers":129}},"volume_usd":{"m5":"82.38758985897","h1":"517.88656321192","h6":"23519.9956156408","h24":"23519.9956156408"},"reserve":"3107.6002","dex":"stonfi"},{"id":"ton_EQB4whdcKBgsDHoG2j9RhTdMdghXAIyPqQzusLSUgMUNUseo","paircoin":{"name":"TINU / TON","baseImg":"https://assets.geckoterminal.com/4dvjymidf47elezccjd0zxvobd1l","quoteImg":"https://assets.coingecko.com/coins/images/17980/small/ton_symbol.png?1696517498","pooladdress":"EQB4whdcKBgsDHoG2j9RhTdMdghXAIyPqQzusLSUgMUNUseo","dexname":"stonfi","basename":"Ton Inu","quotename":"Toncoin","baseSymbol":"TINU","quoteSymbol":"TON","baseaddress":"EQA6Q3dMgVEfXQ9tNBL2fMljEhI_azQ-R3vvPgjGOXwoF7kt","quoteaddress":"EQAAAAAAAAAAAAAAAAAAAAAAAAAAAAAAAAAAAAAAAAAAAM9c","basecoinId":null,"quotecoinId":null},"name":"TINU / TON","basename":"Ton Inu","quotename":"Toncoin","baseSymbol":"TINU","quoteSymbol":"TON","baseImg":"https://assets.geckoterminal.com/4dvjymidf47elezccjd0zxvobd1l","quoteImg":"https://assets.coingecko.com/coins/images/17980/small/ton_symbol.png?1696517498","baseaddress":"EQA6Q3dMgVEfXQ9tNBL2fMljEhI_azQ-R3vvPgjGOXwoF7kt","quoteaddress":"EQAAAAAAAAAAAAAAAAAAAAAAAAAAAAAAAAAAAAAAAAAAAM9c","basecoinId":null,"quotecoinId":null,"created":"2024-01-07T22:23:01Z","pooladdress":"EQB4whdcKBgsDHoG2j9RhTdMdghXAIyPqQzusLSUgMUNUseo","baseprice":"0.00309900137634333","quoteprice":"4.07","fdv":"3099001","cap":null,"price_change_percentage":{"m5":"-0.57","h1":"-4.02","h6":"-12.72","h24":"-14.61"},"transactions":{"m5":{"buys":1,"sells":2,"buyers":1,"sellers":2},"m15":{"buys":1,"sells":3,"buyers":1,"sellers":3},"m30":{"buys":5,"sells":6,"buyers":5,"sellers":5},"h1":{"buys":10,"sells":8,"buyers":10,"sellers":7},"h24":{"buys":307,"sells":271,"buyers":248,"sellers":202}},"volume_usd":{"m5":"1540.32405171348","h1":"4946.20950025471","h6":"32057.9491775974","h24":"144687.599007264"},"reserve":"111462.2907","dex":"stonfi"},{"id":"ton_EQDhSzSqpRsWzXp6fgll5LPshwR1Pyww-3x8VA84VBCUey7U","paircoin":{"name":"SAFET / TON","baseImg":"https://assets.geckoterminal.com/q0bv9eglbbz2sfo8dltpfs45y6ct","quoteImg":"https://assets.coingecko.com/coins/images/17980/small/ton_symbol.png?1696517498","pooladdress":"EQDhSzSqpRsWzXp6fgll5LPshwR1Pyww-3x8VA84VBCUey7U","dexname":"stonfi","basename":"SafemoonTon","quotename":"Toncoin","baseSymbol":"SAFET","quoteSymbol":"TON","baseaddress":"EQBgLw3RLkELgOJUU1oHtHzwkoTdb4RgfT8IgTG6k_iLneEc","quoteaddress":"EQAAAAAAAAAAAAAAAAAAAAAAAAAAAAAAAAAAAAAAAAAAAM9c","basecoinId":null,"quotecoinId":null},"name":"SAFET / TON","basename":"SafemoonTon","quotename":"Toncoin","baseSymbol":"SAFET","quoteSymbol":"TON","baseImg":"https://assets.geckoterminal.com/q0bv9eglbbz2sfo8dltpfs45y6ct","quoteImg":"https://assets.coingecko.com/coins/images/17980/small/ton_symbol.png?1696517498","baseaddress":"EQBgLw3RLkELgOJUU1oHtHzwkoTdb4RgfT8IgTG6k_iLneEc","quoteaddress":"EQAAAAAAAAAAAAAAAAAAAAAAAAAAAAAAAAAAAAAAAAAAAM9c","basecoinId":null,"quotecoinId":null,"created":"2024-03-11T20:13:04Z","pooladdress":"EQDhSzSqpRsWzXp6fgll5LPshwR1Pyww-3x8VA84VBCUey7U","baseprice":"0.0000011712415310061","quoteprice":"4.07","fdv":"1171242","cap":null,"price_change_percentage":{"m5":"0.42","h1":"-2.56","h6":"9.76","h24":"-3.54"},"transactions":{"m5":{"buys":3,"sells":1,"buyers":3,"sellers":1},"m15":{"buys":3,"sells":1,"buyers":3,"sellers":1},"m30":{"buys":4,"sells":1,"buyers":4,"sellers":1},"h1":{"buys":7,"sells":6,"buyers":6,"sellers":6},"h24":{"buys":388,"sells":171,"buyers":316,"sellers":144}},"volume_usd":{"m5":"473.11563048178","h1":"2921.78841019707","h6":"29545.2516578987","h24":"128901.319030509"},"reserve":"231204.1763","dex":"stonfi"},{"id":"ton_EQCxJlFTDDKhCHO_v71J-t76ZmOwDuIwSsInOYo0IPXq7gp1","paircoin":{"name":"TONNEL / TON","baseImg":"https://assets.geckoterminal.com/xoru911i3ovjarjr7bz853ldesxe","quoteImg":"https://assets.coingecko.com/coins/images/17980/small/ton_symbol.png?1696517498","pooladdress":"EQCxJlFTDDKhCHO_v71J-t76ZmOwDuIwSsInOYo0IPXq7gp1","dexname":"stonfi","basename":"Tonnel Network Token","quotename":"Toncoin","baseSymbol":"TONNEL","quoteSymbol":"TON","baseaddress":"EQDNDv54v_TEU5t26rFykylsdPQsv5nsSZaH_v7JSJPtMitv","quoteaddress":"EQAAAAAAAAAAAAAAAAAAAAAAAAAAAAAAAAAAAAAAAAAAAM9c","basecoinId":null,"quotecoinId":null},"name":"TONNEL / TON","basename":"Tonnel Network Token","quotename":"Toncoin","baseSymbol":"TONNEL","quoteSymbol":"TON","baseImg":"https://assets.geckoterminal.com/xoru911i3ovjarjr7bz853ldesxe","quoteImg":"https://assets.coingecko.com/coins/images/17980/small/ton_symbol.png?1696517498","baseaddress":"EQDNDv54v_TEU5t26rFykylsdPQsv5nsSZaH_v7JSJPtMitv","quoteaddress":"EQAAAAAAAAAAAAAAAAAAAAAAAAAAAAAAAAAAAAAAAAAAAM9c","basecoinId":null,"quotecoinId":null,"created":"2023-11-20T03:07:17Z","pooladdress":"EQCxJlFTDDKhCHO_v71J-t76ZmOwDuIwSsInOYo0IPXq7gp1","baseprice":"4.130108876806","quoteprice":"4.07","fdv":"2369685","cap":null,"price_change_percentage":{"m5":"0","h1":"1.26","h6":"0.09","h24":"-12"},"transactions":{"m5":{"buys":0,"sells":0,"buyers":0,"sellers":0},"m15":{"buys":0,"sells":1,"buyers":0,"sellers":1},"m30":{"buys":2,"sells":3,"buyers":2,"sellers":3},"h1":{"buys":4,"sells":5,"buyers":4,"sellers":5},"h24":{"buys":151,"sells":396,"buyers":102,"sellers":345}},"volume_usd":{"m5":"0.0","h1":"553.37987525177","h6":"14724.6493766108","h24":"100571.785349672"},"reserve":"93585.0481","dex":"stonfi"},{"id":"ton_EQCgMzlDFer3XqOnuQpELXeGSMBjV_6PWfWLElvaa3qv2ZUM","paircoin":{"name":"Magic Crystal / TON","baseImg":"https://assets.coingecko.com/coins/images/36120/small/logo.png?1710494969","quoteImg":"https://assets.coingecko.com/coins/images/17980/small/ton_symbol.png?1696517498","pooladdress":"EQCgMzlDFer3XqOnuQpELXeGSMBjV_6PWfWLElvaa3qv2ZUM","dexname":"stonfi","basename":"MC","quotename":"Toncoin","baseSymbol":"Magic Crystal","quoteSymbol":"TON","baseaddress":"EQCbKMTmEAdSnzsK85LOpaDkDH3HjujEbTePMSeirvEaNq-U","quoteaddress":"EQAAAAAAAAAAAAAAAAAAAAAAAAAAAAAAAAAAAAAAAAAAAM9c","basecoinId":"magic-crystal","quotecoinId":null},"name":"Magic Crystal / TON","basename":"MC","quotename":"Toncoin","baseSymbol":"Magic Crystal","quoteSymbol":"TON","baseImg":"https://assets.coingecko.com/coins/images/36120/small/logo.png?1710494969","quoteImg":"https://assets.coingecko.com/coins/images/17980/small/ton_symbol.png?1696517498","baseaddress":"EQCbKMTmEAdSnzsK85LOpaDkDH3HjujEbTePMSeirvEaNq-U","quoteaddress":"EQAAAAAAAAAAAAAAAAAAAAAAAAAAAAAAAAAAAAAAAAAAAM9c","basecoinId":"magic-crystal","quotecoinId":null,"created":"2023-11-20T03:07:21Z","pooladdress":"EQCgMzlDFer3XqOnuQpELXeGSMBjV_6PWfWLElvaa3qv2ZUM","baseprice":"2.81844732214574","quoteprice":"4.07","fdv":"28184473","cap":null,"price_change_percentage":{"m5":"0","h1":"2.41","h6":"1.22","h24":"-4.04"},"transactions":{"m5":{"buys":0,"sells":0,"buyers":0,"sellers":0},"m15":{"buys":1,"sells":0,"buyers":1,"sellers":0},"m30":{"buys":2,"sells":1,"buyers":2,"sellers":1},"h1":{"buys":13,"sells":4,"buyers":13,"sellers":4},"h24":{"buys":353,"sells":188,"buyers":274,"sellers":148}},"volume_usd":{"m5":"0.0","h1":"4649.43229747083","h6":"42383.0263549874","h24":"138313.809614409"},"reserve":"997165.9838","dex":"stonfi"},{"id":"ton_EQCrxPGqBsiGzC7EUlGsEQl7zvbpcQ9TicQB3kpw8HVuT_CH","paircoin":{"name":"LAVE / TON","baseImg":"https://assets.coingecko.com/coins/images/31362/small/logo200.png?1696530179","quoteImg":"https://assets.coingecko.com/coins/images/17980/small/ton_symbol.png?1696517498","pooladdress":"EQCrxPGqBsiGzC7EUlGsEQl7zvbpcQ9TicQB3kpw8HVuT_CH","dexname":"stonfi","basename":"Lavandos","quotename":"Toncoin","baseSymbol":"LAVE","quoteSymbol":"TON","baseaddress":"EQBl3gg6AAdjgjO2ZoNU5Q5EzUIl8XMNZrix8Z5dJmkHUfxI","quoteaddress":"EQAAAAAAAAAAAAAAAAAAAAAAAAAAAAAAAAAAAAAAAAAAAM9c","basecoinId":"lavandos","quotecoinId":null},"name":"LAVE / TON","basename":"Lavandos","quotename":"Toncoin","baseSymbol":"LAVE","quoteSymbol":"TON","baseImg":"https://assets.coingecko.com/coins/images/31362/small/logo200.png?1696530179","quoteImg":"https://assets.coingecko.com/coins/images/17980/small/ton_symbol.png?1696517498","baseaddress":"EQBl3gg6AAdjgjO2ZoNU5Q5EzUIl8XMNZrix8Z5dJmkHUfxI","quoteaddress":"EQAAAAAAAAAAAAAAAAAAAAAAAAAAAAAAAAAAAAAAAAAAAM9c","basecoinId":"lavandos","quotecoinId":null,"created":"2023-11-20T03:07:14Z","pooladdress":"EQCrxPGqBsiGzC7EUlGsEQl7zvbpcQ9TicQB3kpw8HVuT_CH","baseprice":"0.000263643272671432","quoteprice":"4.07","fdv":"1212759","cap":null,"price_change_percentage":{"m5":"0.24","h1":"1.84","h6":"-0.28","h24":"7.25"},"transactions":{"m5":{"buys":2,"sells":0,"buyers":2,"sellers":0},"m15":{"buys":4,"sells":2,"buyers":3,"sellers":2},"m30":{"buys":4,"sells":2,"buyers":3,"sellers":2},"h1":{"buys":8,"sells":2,"buyers":7,"sellers":2},"h24":{"buys":299,"sells":166,"buyers":241,"sellers":103}},"volume_usd":{"m5":"57.7960141616","h1":"730.04978071528","h6":"3854.67301415644","h24":"70418.903057418"},"reserve":"48484.442","dex":"stonfi"}]